{
  "season": 2025,
  "week": 1,
  "propTypes": [
    "PASSING_ATTEMPTS",
    "PASSING_COMPLETIONS",
    "RECEPTIONS",
    "RUSHING_ATTEMPTS"
  ],
  "excludedPropTypes": [
    "PASSING_YARDS",
    "RECEIVING_YARDS",
    "RUSHING_YARDS"
  ],
  "pregameOnly": true,
  "generatedAt": "2026-05-21T00:51:15.001Z",
  "algorithmMode": "V1_SCORECARD",
  "candidates": [
    {
      "id": "2025-w1-fixture-w1-pm-mahomes-passatt",
      "season": 2025,
      "week": 1,
      "gameId": "fixture-kc-at-bal-w1",
      "playerId": "fixture-mahomes",
      "playerName": "Patrick Mahomes",
      "team": "KC",
      "opponent": "BAL",
      "propType": "PASSING_ATTEMPTS",
      "line": 32.5,
      "lineBucket": "29.5 – 32.5",
      "marketOverProbability": 0.5238095238095238,
      "marketUnderProbability": 0.5238095238095238,
      "modelOverProbability": 0.858011578565966,
      "modelUnderProbability": 0.141988421434034,
      "edge": 0.358011578565966,
      "edgeBucket": "≥ 10%",
      "recommendation": "OVER",
      "qualified": true,
      "confidence": 0.8924568452380952,
      "confidenceBucket": "High",
      "disqualifiers": [],
      "riskScore": 0.6622842261904762,
      "dataQualityScore": 0.55,
      "roleStabilityScore": 0.55,
      "weatherRiskScore": 0.71875,
      "injuryRiskScore": 0.85,
      "coachingUncertaintyScore": 8,
      "correlationRiskScore": 0.7,
      "overOdds": -110,
      "underOdds": -110,
      "selectedOdds": -110,
      "selectedSide": "OVER",
      "actualStat": null,
      "result": "PASS",
      "profitLossUnits": 0,
      "counterfactualResult": "NO_RESULT",
      "counterfactualProfitLossUnits": 0,
      "postmortemTags": [],
      "scorecardSnapshot": {
        "scenarioName": "bt-2025-w1-fixture-w1-pm-mahomes-passatt",
        "propId": "fixture-w1-pm-mahomes-passatt",
        "playerName": "Patrick Mahomes",
        "propType": "PASSING_ATTEMPTS",
        "marketLine": 32.5,
        "overOdds": -110,
        "underOdds": -110,
        "marketOverProbability": 0.5238095238095238,
        "marketUnderProbability": 0.5238095238095238,
        "noVigOverProbability": 0.5,
        "noVigUnderProbability": 0.5,
        "projectedMean": 37,
        "projectedStdDev": 4.2,
        "modelOverProbability": 0.858011578565966,
        "modelUnderProbability": 0.141988421434034,
        "edgeOver": 0.358011578565966,
        "edgeUnder": -0.358011578565966,
        "selectedSide": "OVER",
        "edgeThreshold": 0.04,
        "recommendation": "OVER",
        "qualified": true,
        "confidence": 0.8924568452380952,
        "volatilityLevel": "low",
        "dataQualityScore": 0.55,
        "riskScore": 0.6622842261904762,
        "roleStabilityScore": 0.55,
        "gameScriptScore": 0.7857142857142857,
        "paceScore": 0.62,
        "marketContextScore": 0.5238095238095233,
        "weatherEnvironmentScore": 0.71875,
        "injuryContextScore": 0.85,
        "correlationExposureScore": 0.7,
        "passReasons": [
          "Model edge of +35.8% on OVER clears 4.0% threshold",
          "Model projects 85.8% hit rate vs no-vig 50.0%",
          "Composite risk score 0.66 clears all gates",
          "KC 2026 (Weeks 1-4): blend favors prior-year team (70%). Continuity 88, uncertainty penalty 8. Default profile for teams without explicitly encoded 2026 staff transition signal."
        ],
        "failReasons": [],
        "reasons": [
          "Model edge of +35.8% on OVER clears 4.0% threshold",
          "Model projects 85.8% hit rate vs no-vig 50.0%",
          "Composite risk score 0.66 clears all gates",
          "KC 2026 (Weeks 1-4): blend favors prior-year team (70%). Continuity 88, uncertainty penalty 8. Default profile for teams without explicitly encoded 2026 staff transition signal."
        ],
        "risks": [
          "Market context 0.52 (above 0.45 gate but below 0.65 comfort zone)",
          "Data quality 0.55 (above 0.55 gate but below 0.65 comfort zone)",
          "Role stability 0.55 (above 0.55 gate but below 0.65 comfort zone)",
          "Pace 0.62 (above 0.45 gate but below 0.65 comfort zone)",
          "Low coaching uncertainty — context informational only"
        ],
        "disqualifiers": [],
        "finalExplanation": "OVER qualifies on Patrick Mahomes PASSING_ATTEMPTS 32.5: model edge of +35.8% clears 4.0% threshold and all risk gates pass (composite 0.66).",
        "coachingTransition": {
          "team": "KC",
          "season": 2026,
          "scores": {
            "coachingContinuityScore": 88,
            "offensivePlayCallerChangeScore": 0,
            "defensivePlayCallerChangeScore": 0,
            "teamTendencyTrustScore": 82,
            "offensiveIdentityShiftScore": 8,
            "defensiveIdentityShiftScore": 8,
            "playCallerConfidenceScore": 95,
            "coachingUncertaintyPenalty": 8
          },
          "blendWeights": {
            "priorTeam": 70,
            "coachProfile": 20,
            "leagueAverage": 10,
            "currentSeasonObserved": 0
          },
          "offensiveNotes": [],
          "defensiveNotes": [],
          "propImpacts": {
            "PASSING_ATTEMPTS": "neutral",
            "PASSING_COMPLETIONS": "neutral",
            "PASSING_YARDS": "neutral",
            "RECEPTIONS": "neutral",
            "RECEIVING_YARDS": "neutral",
            "RUSHING_ATTEMPTS": "neutral",
            "RUSHING_YARDS": "neutral"
          },
          "warnings": [
            "Low coaching uncertainty — context informational only"
          ],
          "summary": "KC 2026 (Weeks 1-4): blend favors prior-year team (70%). Continuity 88, uncertainty penalty 8. Default profile for teams without explicitly encoded 2026 staff transition signal."
        }
      },
      "createdAt": "2026-05-21T00:51:14.998Z"
    },
    {
      "id": "2025-w1-fixture-w1-pm-mahomes-passcomp",
      "season": 2025,
      "week": 1,
      "gameId": "fixture-kc-at-bal-w1",
      "playerId": "fixture-mahomes",
      "playerName": "Patrick Mahomes",
      "team": "KC",
      "opponent": "BAL",
      "propType": "PASSING_COMPLETIONS",
      "line": 22.5,
      "lineBucket": "19.5 – 22.5",
      "marketOverProbability": 0.5348837209302325,
      "marketUnderProbability": 0.5121951219512195,
      "modelOverProbability": 0.8331446553267421,
      "modelUnderProbability": 0.1668553446732579,
      "edge": 0.32231041914039327,
      "edgeBucket": "≥ 10%",
      "recommendation": "OVER",
      "qualified": true,
      "confidence": 0.8925918964224941,
      "confidenceBucket": "High",
      "disqualifiers": [],
      "riskScore": 0.6629594821124706,
      "dataQualityScore": 0.55,
      "roleStabilityScore": 0.55,
      "weatherRiskScore": 0.71875,
      "injuryRiskScore": 0.85,
      "coachingUncertaintyScore": 8,
      "correlationRiskScore": 0.7,
      "overOdds": -115,
      "underOdds": -105,
      "selectedOdds": -115,
      "selectedSide": "OVER",
      "actualStat": null,
      "result": "PASS",
      "profitLossUnits": 0,
      "counterfactualResult": "NO_RESULT",
      "counterfactualProfitLossUnits": 0,
      "postmortemTags": [],
      "scorecardSnapshot": {
        "scenarioName": "bt-2025-w1-fixture-w1-pm-mahomes-passcomp",
        "propId": "fixture-w1-pm-mahomes-passcomp",
        "playerName": "Patrick Mahomes",
        "propType": "PASSING_COMPLETIONS",
        "marketLine": 22.5,
        "overOdds": -115,
        "underOdds": -105,
        "marketOverProbability": 0.5348837209302325,
        "marketUnderProbability": 0.5121951219512195,
        "noVigOverProbability": 0.5108342361863488,
        "noVigUnderProbability": 0.4891657638136512,
        "projectedMean": 25.4,
        "projectedStdDev": 3,
        "modelOverProbability": 0.8331446553267421,
        "modelUnderProbability": 0.1668553446732579,
        "edgeOver": 0.32231041914039327,
        "edgeUnder": -0.32231041914039327,
        "selectedSide": "OVER",
        "edgeThreshold": 0.04,
        "recommendation": "OVER",
        "qualified": true,
        "confidence": 0.8925918964224941,
        "volatilityLevel": "low",
        "dataQualityScore": 0.55,
        "riskScore": 0.6629594821124706,
        "roleStabilityScore": 0.55,
        "gameScriptScore": 0.7857142857142857,
        "paceScore": 0.62,
        "marketContextScore": 0.5292115711854786,
        "weatherEnvironmentScore": 0.71875,
        "injuryContextScore": 0.85,
        "correlationExposureScore": 0.7,
        "passReasons": [
          "Model edge of +32.2% on OVER clears 4.0% threshold",
          "Model projects 83.3% hit rate vs no-vig 51.1%",
          "Composite risk score 0.66 clears all gates",
          "KC 2026 (Weeks 1-4): blend favors prior-year team (70%). Continuity 88, uncertainty penalty 8. Default profile for teams without explicitly encoded 2026 staff transition signal."
        ],
        "failReasons": [],
        "reasons": [
          "Model edge of +32.2% on OVER clears 4.0% threshold",
          "Model projects 83.3% hit rate vs no-vig 51.1%",
          "Composite risk score 0.66 clears all gates",
          "KC 2026 (Weeks 1-4): blend favors prior-year team (70%). Continuity 88, uncertainty penalty 8. Default profile for teams without explicitly encoded 2026 staff transition signal."
        ],
        "risks": [
          "Market context 0.53 (above 0.45 gate but below 0.65 comfort zone)",
          "Data quality 0.55 (above 0.55 gate but below 0.65 comfort zone)",
          "Role stability 0.55 (above 0.55 gate but below 0.65 comfort zone)",
          "Pace 0.62 (above 0.45 gate but below 0.65 comfort zone)",
          "Low coaching uncertainty — context informational only"
        ],
        "disqualifiers": [],
        "finalExplanation": "OVER qualifies on Patrick Mahomes PASSING_COMPLETIONS 22.5: model edge of +32.2% clears 4.0% threshold and all risk gates pass (composite 0.66).",
        "coachingTransition": {
          "team": "KC",
          "season": 2026,
          "scores": {
            "coachingContinuityScore": 88,
            "offensivePlayCallerChangeScore": 0,
            "defensivePlayCallerChangeScore": 0,
            "teamTendencyTrustScore": 82,
            "offensiveIdentityShiftScore": 8,
            "defensiveIdentityShiftScore": 8,
            "playCallerConfidenceScore": 95,
            "coachingUncertaintyPenalty": 8
          },
          "blendWeights": {
            "priorTeam": 70,
            "coachProfile": 20,
            "leagueAverage": 10,
            "currentSeasonObserved": 0
          },
          "offensiveNotes": [],
          "defensiveNotes": [],
          "propImpacts": {
            "PASSING_ATTEMPTS": "neutral",
            "PASSING_COMPLETIONS": "neutral",
            "PASSING_YARDS": "neutral",
            "RECEPTIONS": "neutral",
            "RECEIVING_YARDS": "neutral",
            "RUSHING_ATTEMPTS": "neutral",
            "RUSHING_YARDS": "neutral"
          },
          "warnings": [
            "Low coaching uncertainty — context informational only"
          ],
          "summary": "KC 2026 (Weeks 1-4): blend favors prior-year team (70%). Continuity 88, uncertainty penalty 8. Default profile for teams without explicitly encoded 2026 staff transition signal."
        }
      },
      "createdAt": "2026-05-21T00:51:14.998Z"
    },
    {
      "id": "2025-w1-fixture-w1-pm-kelce-receptions",
      "season": 2025,
      "week": 1,
      "gameId": "fixture-kc-at-bal-w1",
      "playerId": "fixture-kelce",
      "playerName": "Travis Kelce",
      "team": "KC",
      "opponent": "BAL",
      "propType": "RECEPTIONS",
      "line": 5.5,
      "lineBucket": "5.5",
      "marketOverProbability": 0.5238095238095238,
      "marketUnderProbability": 0.5238095238095238,
      "modelOverProbability": 0.691462462723994,
      "modelUnderProbability": 0.3085375372760059,
      "edge": 0.19146246272399403,
      "edgeBucket": "≥ 10%",
      "recommendation": "PASS",
      "qualified": false,
      "confidence": 0.4351693079620893,
      "confidenceBucket": "Low",
      "primaryDisqualifier": "Role stability score 0.50 below 0.55 gate",
      "disqualifiers": [
        "Role stability score 0.50 below 0.55 gate"
      ],
      "riskScore": 0.6685342261904761,
      "dataQualityScore": 0.55,
      "roleStabilityScore": 0.5,
      "weatherRiskScore": 0.71875,
      "injuryRiskScore": 0.85,
      "coachingUncertaintyScore": 8,
      "correlationRiskScore": 0.8,
      "overOdds": -110,
      "underOdds": -110,
      "selectedOdds": -110,
      "selectedSide": "OVER",
      "actualStat": null,
      "result": "PASS",
      "profitLossUnits": 0,
      "counterfactualResult": "NO_RESULT",
      "counterfactualProfitLossUnits": 0,
      "postmortemTags": [],
      "scorecardSnapshot": {
        "scenarioName": "bt-2025-w1-fixture-w1-pm-kelce-receptions",
        "propId": "fixture-w1-pm-kelce-receptions",
        "playerName": "Travis Kelce",
        "propType": "RECEPTIONS",
        "marketLine": 5.5,
        "overOdds": -110,
        "underOdds": -110,
        "marketOverProbability": 0.5238095238095238,
        "marketUnderProbability": 0.5238095238095238,
        "noVigOverProbability": 0.5,
        "noVigUnderProbability": 0.5,
        "projectedMean": 6.2,
        "projectedStdDev": 1.4,
        "modelOverProbability": 0.691462462723994,
        "modelUnderProbability": 0.3085375372760059,
        "edgeOver": 0.19146246272399403,
        "edgeUnder": -0.1914624627239941,
        "selectedSide": "OVER",
        "edgeThreshold": 0.04,
        "recommendation": "PASS",
        "qualified": false,
        "confidence": 0.4351693079620893,
        "volatilityLevel": "medium",
        "dataQualityScore": 0.55,
        "riskScore": 0.6685342261904761,
        "roleStabilityScore": 0.5,
        "gameScriptScore": 0.7857142857142857,
        "paceScore": 0.62,
        "marketContextScore": 0.5238095238095233,
        "weatherEnvironmentScore": 0.71875,
        "injuryContextScore": 0.85,
        "correlationExposureScore": 0.8,
        "passReasons": [
          "Model edge of +19.1% on OVER clears 4.0% threshold",
          "Model projects 69.1% hit rate vs no-vig 50.0%"
        ],
        "failReasons": [
          "Role stability 0.50 below 0.55 gate"
        ],
        "reasons": [
          "Role stability 0.50 below 0.55 gate"
        ],
        "risks": [
          "Market context 0.52 (above 0.45 gate but below 0.65 comfort zone)",
          "Data quality 0.55 (above 0.55 gate but below 0.65 comfort zone)",
          "Pace 0.62 (above 0.45 gate but below 0.65 comfort zone)",
          "Role stability 0.50 below 0.55 gate",
          "Low coaching uncertainty — context informational only"
        ],
        "disqualifiers": [
          "Role stability score 0.50 below 0.55 gate"
        ],
        "finalExplanation": "PASS on Travis Kelce RECEPTIONS 5.5: OVER edge of +19.1% would qualify, but role stability score 0.50 is below the 0.55 gate.",
        "coachingTransition": {
          "team": "KC",
          "season": 2026,
          "scores": {
            "coachingContinuityScore": 88,
            "offensivePlayCallerChangeScore": 0,
            "defensivePlayCallerChangeScore": 0,
            "teamTendencyTrustScore": 82,
            "offensiveIdentityShiftScore": 8,
            "defensiveIdentityShiftScore": 8,
            "playCallerConfidenceScore": 95,
            "coachingUncertaintyPenalty": 8
          },
          "blendWeights": {
            "priorTeam": 70,
            "coachProfile": 20,
            "leagueAverage": 10,
            "currentSeasonObserved": 0
          },
          "offensiveNotes": [],
          "defensiveNotes": [],
          "propImpacts": {
            "PASSING_ATTEMPTS": "neutral",
            "PASSING_COMPLETIONS": "neutral",
            "PASSING_YARDS": "neutral",
            "RECEPTIONS": "neutral",
            "RECEIVING_YARDS": "neutral",
            "RUSHING_ATTEMPTS": "neutral",
            "RUSHING_YARDS": "neutral"
          },
          "warnings": [
            "Low coaching uncertainty — context informational only"
          ],
          "summary": "KC 2026 (Weeks 1-4): blend favors prior-year team (70%). Continuity 88, uncertainty penalty 8. Default profile for teams without explicitly encoded 2026 staff transition signal."
        }
      },
      "createdAt": "2026-05-21T00:51:14.998Z"
    },
    {
      "id": "2025-w1-fixture-w1-pm-pacheco-rushatt",
      "season": 2025,
      "week": 1,
      "gameId": "fixture-kc-at-bal-w1",
      "playerId": "fixture-pacheco",
      "playerName": "Isiah Pacheco",
      "team": "KC",
      "opponent": "BAL",
      "propType": "RUSHING_ATTEMPTS",
      "line": 13.5,
      "lineBucket": "10.5 – 14.5",
      "marketOverProbability": 0.5348837209302325,
      "marketUnderProbability": 0.5121951219512195,
      "modelOverProbability": 0.7475075278364188,
      "modelUnderProbability": 0.25249247216358117,
      "edge": 0.23667329165007,
      "edgeBucket": "≥ 10%",
      "recommendation": "PASS",
      "qualified": false,
      "confidence": 0.4471231464224941,
      "confidenceBucket": "Low",
      "primaryDisqualifier": "Role stability score 0.50 below 0.55 gate",
      "disqualifiers": [
        "Role stability score 0.50 below 0.55 gate"
      ],
      "riskScore": 0.6856157321124706,
      "dataQualityScore": 0.55,
      "roleStabilityScore": 0.5,
      "weatherRiskScore": 0.85,
      "injuryRiskScore": 0.85,
      "coachingUncertaintyScore": 8,
      "correlationRiskScore": 0.8,
      "overOdds": -115,
      "underOdds": -105,
      "selectedOdds": -115,
      "selectedSide": "OVER",
      "actualStat": null,
      "result": "PASS",
      "profitLossUnits": 0,
      "counterfactualResult": "NO_RESULT",
      "counterfactualProfitLossUnits": 0,
      "postmortemTags": [],
      "scorecardSnapshot": {
        "scenarioName": "bt-2025-w1-fixture-w1-pm-pacheco-rushatt",
        "propId": "fixture-w1-pm-pacheco-rushatt",
        "playerName": "Isiah Pacheco",
        "propType": "RUSHING_ATTEMPTS",
        "marketLine": 13.5,
        "overOdds": -115,
        "underOdds": -105,
        "marketOverProbability": 0.5348837209302325,
        "marketUnderProbability": 0.5121951219512195,
        "noVigOverProbability": 0.5108342361863488,
        "noVigUnderProbability": 0.4891657638136512,
        "projectedMean": 15.5,
        "projectedStdDev": 3,
        "modelOverProbability": 0.7475075278364188,
        "modelUnderProbability": 0.25249247216358117,
        "edgeOver": 0.23667329165007,
        "edgeUnder": -0.23667329165007,
        "selectedSide": "OVER",
        "edgeThreshold": 0.04,
        "recommendation": "PASS",
        "qualified": false,
        "confidence": 0.4471231464224941,
        "volatilityLevel": "medium",
        "dataQualityScore": 0.55,
        "riskScore": 0.6856157321124706,
        "roleStabilityScore": 0.5,
        "gameScriptScore": 0.7857142857142857,
        "paceScore": 0.62,
        "marketContextScore": 0.5292115711854786,
        "weatherEnvironmentScore": 0.85,
        "injuryContextScore": 0.85,
        "correlationExposureScore": 0.8,
        "passReasons": [
          "Model edge of +23.7% on OVER clears 4.0% threshold",
          "Model projects 74.8% hit rate vs no-vig 51.1%"
        ],
        "failReasons": [
          "Role stability 0.50 below 0.55 gate"
        ],
        "reasons": [
          "Role stability 0.50 below 0.55 gate"
        ],
        "risks": [
          "Market context 0.53 (above 0.45 gate but below 0.65 comfort zone)",
          "Data quality 0.55 (above 0.55 gate but below 0.65 comfort zone)",
          "Pace 0.62 (above 0.45 gate but below 0.65 comfort zone)",
          "Role stability 0.50 below 0.55 gate",
          "Low coaching uncertainty — context informational only"
        ],
        "disqualifiers": [
          "Role stability score 0.50 below 0.55 gate"
        ],
        "finalExplanation": "PASS on Isiah Pacheco RUSHING_ATTEMPTS 13.5: OVER edge of +23.7% would qualify, but role stability score 0.50 is below the 0.55 gate.",
        "coachingTransition": {
          "team": "KC",
          "season": 2026,
          "scores": {
            "coachingContinuityScore": 88,
            "offensivePlayCallerChangeScore": 0,
            "defensivePlayCallerChangeScore": 0,
            "teamTendencyTrustScore": 82,
            "offensiveIdentityShiftScore": 8,
            "defensiveIdentityShiftScore": 8,
            "playCallerConfidenceScore": 95,
            "coachingUncertaintyPenalty": 8
          },
          "blendWeights": {
            "priorTeam": 70,
            "coachProfile": 20,
            "leagueAverage": 10,
            "currentSeasonObserved": 0
          },
          "offensiveNotes": [],
          "defensiveNotes": [],
          "propImpacts": {
            "PASSING_ATTEMPTS": "neutral",
            "PASSING_COMPLETIONS": "neutral",
            "PASSING_YARDS": "neutral",
            "RECEPTIONS": "neutral",
            "RECEIVING_YARDS": "neutral",
            "RUSHING_ATTEMPTS": "neutral",
            "RUSHING_YARDS": "neutral"
          },
          "warnings": [
            "Low coaching uncertainty — context informational only"
          ],
          "summary": "KC 2026 (Weeks 1-4): blend favors prior-year team (70%). Continuity 88, uncertainty penalty 8. Default profile for teams without explicitly encoded 2026 staff transition signal."
        }
      },
      "createdAt": "2026-05-21T00:51:14.998Z"
    },
    {
      "id": "2025-w1-fixture-w1-pm-allen-passatt",
      "season": 2025,
      "week": 1,
      "gameId": "fixture-buf-at-mia-w1",
      "playerId": "fixture-allen",
      "playerName": "Josh Allen",
      "team": "BUF",
      "opponent": "MIA",
      "propType": "PASSING_ATTEMPTS",
      "line": 31.5,
      "lineBucket": "29.5 – 32.5",
      "marketOverProbability": 0.5238095238095238,
      "marketUnderProbability": 0.5238095238095238,
      "modelOverProbability": 0.7340145270237729,
      "modelUnderProbability": 0.2659854729762271,
      "edge": 0.2340145270237729,
      "edgeBucket": "≥ 10%",
      "recommendation": "PASS",
      "qualified": false,
      "confidence": 0.3901934523809524,
      "confidenceBucket": "Low",
      "primaryDisqualifier": "Role stability score 0.50 below 0.55 gate",
      "disqualifiers": [
        "Role stability score 0.50 below 0.55 gate"
      ],
      "riskScore": 0.6509672619047617,
      "dataQualityScore": 0.55,
      "roleStabilityScore": 0.5,
      "weatherRiskScore": 0.5625,
      "injuryRiskScore": 0.85,
      "coachingUncertaintyScore": 18,
      "correlationRiskScore": 0.7,
      "overOdds": -110,
      "underOdds": -110,
      "selectedOdds": -110,
      "selectedSide": "OVER",
      "actualStat": null,
      "result": "PASS",
      "profitLossUnits": 0,
      "counterfactualResult": "NO_RESULT",
      "counterfactualProfitLossUnits": 0,
      "postmortemTags": [],
      "scorecardSnapshot": {
        "scenarioName": "bt-2025-w1-fixture-w1-pm-allen-passatt",
        "propId": "fixture-w1-pm-allen-passatt",
        "playerName": "Josh Allen",
        "propType": "PASSING_ATTEMPTS",
        "marketLine": 31.5,
        "overOdds": -110,
        "underOdds": -110,
        "marketOverProbability": 0.5238095238095238,
        "marketUnderProbability": 0.5238095238095238,
        "noVigOverProbability": 0.5,
        "noVigUnderProbability": 0.5,
        "projectedMean": 34,
        "projectedStdDev": 4,
        "modelOverProbability": 0.7340145270237729,
        "modelUnderProbability": 0.2659854729762271,
        "edgeOver": 0.2340145270237729,
        "edgeUnder": -0.2340145270237729,
        "selectedSide": "OVER",
        "edgeThreshold": 0.04,
        "recommendation": "PASS",
        "qualified": false,
        "confidence": 0.3901934523809524,
        "volatilityLevel": "low",
        "dataQualityScore": 0.55,
        "riskScore": 0.6509672619047617,
        "roleStabilityScore": 0.5,
        "gameScriptScore": 0.8214285714285714,
        "paceScore": 0.7,
        "marketContextScore": 0.5238095238095233,
        "weatherEnvironmentScore": 0.5625,
        "injuryContextScore": 0.85,
        "correlationExposureScore": 0.7,
        "passReasons": [
          "Model edge of +23.4% on OVER clears 4.0% threshold",
          "Model projects 73.4% hit rate vs no-vig 50.0%"
        ],
        "failReasons": [
          "Role stability 0.50 below 0.55 gate"
        ],
        "reasons": [
          "Role stability 0.50 below 0.55 gate"
        ],
        "risks": [
          "Market context 0.52 (above 0.45 gate but below 0.65 comfort zone)",
          "Data quality 0.55 (above 0.55 gate but below 0.65 comfort zone)",
          "Weather / environment 0.56 (above 0.50 gate but below 0.65 comfort zone)",
          "Role stability 0.50 below 0.55 gate",
          "Low coaching uncertainty — context informational only"
        ],
        "disqualifiers": [
          "Role stability score 0.50 below 0.55 gate"
        ],
        "finalExplanation": "PASS on Josh Allen PASSING_ATTEMPTS 31.5: OVER edge of +23.4% would qualify, but role stability score 0.50 is below the 0.55 gate.",
        "coachingTransition": {
          "team": "BUF",
          "season": 2026,
          "scores": {
            "coachingContinuityScore": 80,
            "offensivePlayCallerChangeScore": 15,
            "defensivePlayCallerChangeScore": 70,
            "teamTendencyTrustScore": 72,
            "offensiveIdentityShiftScore": 20,
            "defensiveIdentityShiftScore": 55,
            "playCallerConfidenceScore": 90,
            "coachingUncertaintyPenalty": 18
          },
          "blendWeights": {
            "priorTeam": 70,
            "coachProfile": 20,
            "leagueAverage": 10,
            "currentSeasonObserved": 0
          },
          "offensiveNotes": [],
          "defensiveNotes": [],
          "propImpacts": {
            "PASSING_ATTEMPTS": "neutral",
            "PASSING_COMPLETIONS": "neutral",
            "PASSING_YARDS": "neutral",
            "RECEPTIONS": "neutral",
            "RECEIVING_YARDS": "neutral",
            "RUSHING_ATTEMPTS": "neutral",
            "RUSHING_YARDS": "neutral"
          },
          "warnings": [
            "Low coaching uncertainty — context informational only"
          ],
          "summary": "BUF 2026 (Weeks 1-4): blend favors prior-year team (70%). Continuity 80, uncertainty penalty 18. Treat offense as mostly stable; defensive/staff title changes should not materially change offensive prop priors."
        }
      },
      "createdAt": "2026-05-21T00:51:14.998Z"
    },
    {
      "id": "2025-w1-fixture-w1-pm-allen-passcomp",
      "season": 2025,
      "week": 1,
      "gameId": "fixture-buf-at-mia-w1",
      "playerId": "fixture-allen",
      "playerName": "Josh Allen",
      "team": "BUF",
      "opponent": "MIA",
      "propType": "PASSING_COMPLETIONS",
      "line": 20.5,
      "lineBucket": "19.5 – 22.5",
      "marketOverProbability": 0.5238095238095238,
      "marketUnderProbability": 0.5238095238095238,
      "modelOverProbability": 0.7580364167128033,
      "modelUnderProbability": 0.24196358328719675,
      "edge": 0.2580364167128033,
      "edgeBucket": "≥ 10%",
      "recommendation": "PASS",
      "qualified": false,
      "confidence": 0.3901934523809524,
      "confidenceBucket": "Low",
      "primaryDisqualifier": "Role stability score 0.50 below 0.55 gate",
      "disqualifiers": [
        "Role stability score 0.50 below 0.55 gate"
      ],
      "riskScore": 0.6509672619047617,
      "dataQualityScore": 0.55,
      "roleStabilityScore": 0.5,
      "weatherRiskScore": 0.5625,
      "injuryRiskScore": 0.85,
      "coachingUncertaintyScore": 18,
      "correlationRiskScore": 0.7,
      "overOdds": -110,
      "underOdds": -110,
      "selectedOdds": -110,
      "selectedSide": "OVER",
      "actualStat": null,
      "result": "PASS",
      "profitLossUnits": 0,
      "counterfactualResult": "NO_RESULT",
      "counterfactualProfitLossUnits": 0,
      "postmortemTags": [],
      "scorecardSnapshot": {
        "scenarioName": "bt-2025-w1-fixture-w1-pm-allen-passcomp",
        "propId": "fixture-w1-pm-allen-passcomp",
        "playerName": "Josh Allen",
        "propType": "PASSING_COMPLETIONS",
        "marketLine": 20.5,
        "overOdds": -110,
        "underOdds": -110,
        "marketOverProbability": 0.5238095238095238,
        "marketUnderProbability": 0.5238095238095238,
        "noVigOverProbability": 0.5,
        "noVigUnderProbability": 0.5,
        "projectedMean": 22.6,
        "projectedStdDev": 3,
        "modelOverProbability": 0.7580364167128033,
        "modelUnderProbability": 0.24196358328719675,
        "edgeOver": 0.2580364167128033,
        "edgeUnder": -0.25803641671280325,
        "selectedSide": "OVER",
        "edgeThreshold": 0.04,
        "recommendation": "PASS",
        "qualified": false,
        "confidence": 0.3901934523809524,
        "volatilityLevel": "low",
        "dataQualityScore": 0.55,
        "riskScore": 0.6509672619047617,
        "roleStabilityScore": 0.5,
        "gameScriptScore": 0.8214285714285714,
        "paceScore": 0.7,
        "marketContextScore": 0.5238095238095233,
        "weatherEnvironmentScore": 0.5625,
        "injuryContextScore": 0.85,
        "correlationExposureScore": 0.7,
        "passReasons": [
          "Model edge of +25.8% on OVER clears 4.0% threshold",
          "Model projects 75.8% hit rate vs no-vig 50.0%"
        ],
        "failReasons": [
          "Role stability 0.50 below 0.55 gate"
        ],
        "reasons": [
          "Role stability 0.50 below 0.55 gate"
        ],
        "risks": [
          "Market context 0.52 (above 0.45 gate but below 0.65 comfort zone)",
          "Data quality 0.55 (above 0.55 gate but below 0.65 comfort zone)",
          "Weather / environment 0.56 (above 0.50 gate but below 0.65 comfort zone)",
          "Role stability 0.50 below 0.55 gate",
          "Low coaching uncertainty — context informational only"
        ],
        "disqualifiers": [
          "Role stability score 0.50 below 0.55 gate"
        ],
        "finalExplanation": "PASS on Josh Allen PASSING_COMPLETIONS 20.5: OVER edge of +25.8% would qualify, but role stability score 0.50 is below the 0.55 gate.",
        "coachingTransition": {
          "team": "BUF",
          "season": 2026,
          "scores": {
            "coachingContinuityScore": 80,
            "offensivePlayCallerChangeScore": 15,
            "defensivePlayCallerChangeScore": 70,
            "teamTendencyTrustScore": 72,
            "offensiveIdentityShiftScore": 20,
            "defensiveIdentityShiftScore": 55,
            "playCallerConfidenceScore": 90,
            "coachingUncertaintyPenalty": 18
          },
          "blendWeights": {
            "priorTeam": 70,
            "coachProfile": 20,
            "leagueAverage": 10,
            "currentSeasonObserved": 0
          },
          "offensiveNotes": [],
          "defensiveNotes": [],
          "propImpacts": {
            "PASSING_ATTEMPTS": "neutral",
            "PASSING_COMPLETIONS": "neutral",
            "PASSING_YARDS": "neutral",
            "RECEPTIONS": "neutral",
            "RECEIVING_YARDS": "neutral",
            "RUSHING_ATTEMPTS": "neutral",
            "RUSHING_YARDS": "neutral"
          },
          "warnings": [
            "Low coaching uncertainty — context informational only"
          ],
          "summary": "BUF 2026 (Weeks 1-4): blend favors prior-year team (70%). Continuity 80, uncertainty penalty 18. Treat offense as mostly stable; defensive/staff title changes should not materially change offensive prop priors."
        }
      },
      "createdAt": "2026-05-21T00:51:14.998Z"
    },
    {
      "id": "2025-w1-fixture-w1-pm-diggs-receptions",
      "season": 2025,
      "week": 1,
      "gameId": "fixture-buf-at-mia-w1",
      "playerId": "fixture-diggs",
      "playerName": "Stefon Diggs",
      "team": "BUF",
      "opponent": "MIA",
      "propType": "RECEPTIONS",
      "line": 5.5,
      "lineBucket": "5.5",
      "marketOverProbability": 0.5454545454545454,
      "marketUnderProbability": 0.5,
      "modelOverProbability": 0.7475075278364188,
      "modelUnderProbability": 0.25249247216358117,
      "edge": 0.22576839740163623,
      "edgeBucket": "≥ 10%",
      "recommendation": "PASS",
      "qualified": false,
      "confidence": 0.39323457792207794,
      "confidenceBucket": "Low",
      "primaryDisqualifier": "Role stability score 0.50 below 0.55 gate",
      "disqualifiers": [
        "Role stability score 0.50 below 0.55 gate"
      ],
      "riskScore": 0.6661728896103897,
      "dataQualityScore": 0.55,
      "roleStabilityScore": 0.5,
      "weatherRiskScore": 0.5625,
      "injuryRiskScore": 0.85,
      "coachingUncertaintyScore": 18,
      "correlationRiskScore": 0.8,
      "overOdds": -120,
      "underOdds": -100,
      "selectedOdds": -120,
      "selectedSide": "OVER",
      "actualStat": null,
      "result": "PASS",
      "profitLossUnits": 0,
      "counterfactualResult": "NO_RESULT",
      "counterfactualProfitLossUnits": 0,
      "postmortemTags": [],
      "scorecardSnapshot": {
        "scenarioName": "bt-2025-w1-fixture-w1-pm-diggs-receptions",
        "propId": "fixture-w1-pm-diggs-receptions",
        "playerName": "Stefon Diggs",
        "propType": "RECEPTIONS",
        "marketLine": 5.5,
        "overOdds": -120,
        "underOdds": -100,
        "marketOverProbability": 0.5454545454545454,
        "marketUnderProbability": 0.5,
        "noVigOverProbability": 0.5217391304347826,
        "noVigUnderProbability": 0.4782608695652174,
        "projectedMean": 6.5,
        "projectedStdDev": 1.5,
        "modelOverProbability": 0.7475075278364188,
        "modelUnderProbability": 0.25249247216358117,
        "edgeOver": 0.22576839740163623,
        "edgeUnder": -0.22576839740163623,
        "selectedSide": "OVER",
        "edgeThreshold": 0.04,
        "recommendation": "PASS",
        "qualified": false,
        "confidence": 0.39323457792207794,
        "volatilityLevel": "medium",
        "dataQualityScore": 0.55,
        "riskScore": 0.6661728896103897,
        "roleStabilityScore": 0.5,
        "gameScriptScore": 0.8214285714285714,
        "paceScore": 0.7,
        "marketContextScore": 0.5454545454545459,
        "weatherEnvironmentScore": 0.5625,
        "injuryContextScore": 0.85,
        "correlationExposureScore": 0.8,
        "passReasons": [
          "Model edge of +22.6% on OVER clears 4.0% threshold",
          "Model projects 74.8% hit rate vs no-vig 52.2%"
        ],
        "failReasons": [
          "Role stability 0.50 below 0.55 gate"
        ],
        "reasons": [
          "Role stability 0.50 below 0.55 gate"
        ],
        "risks": [
          "Market context 0.55 (above 0.45 gate but below 0.65 comfort zone)",
          "Data quality 0.55 (above 0.55 gate but below 0.65 comfort zone)",
          "Weather / environment 0.56 (above 0.50 gate but below 0.65 comfort zone)",
          "Role stability 0.50 below 0.55 gate",
          "Low coaching uncertainty — context informational only"
        ],
        "disqualifiers": [
          "Role stability score 0.50 below 0.55 gate"
        ],
        "finalExplanation": "PASS on Stefon Diggs RECEPTIONS 5.5: OVER edge of +22.6% would qualify, but role stability score 0.50 is below the 0.55 gate.",
        "coachingTransition": {
          "team": "BUF",
          "season": 2026,
          "scores": {
            "coachingContinuityScore": 80,
            "offensivePlayCallerChangeScore": 15,
            "defensivePlayCallerChangeScore": 70,
            "teamTendencyTrustScore": 72,
            "offensiveIdentityShiftScore": 20,
            "defensiveIdentityShiftScore": 55,
            "playCallerConfidenceScore": 90,
            "coachingUncertaintyPenalty": 18
          },
          "blendWeights": {
            "priorTeam": 70,
            "coachProfile": 20,
            "leagueAverage": 10,
            "currentSeasonObserved": 0
          },
          "offensiveNotes": [],
          "defensiveNotes": [],
          "propImpacts": {
            "PASSING_ATTEMPTS": "neutral",
            "PASSING_COMPLETIONS": "neutral",
            "PASSING_YARDS": "neutral",
            "RECEPTIONS": "neutral",
            "RECEIVING_YARDS": "neutral",
            "RUSHING_ATTEMPTS": "neutral",
            "RUSHING_YARDS": "neutral"
          },
          "warnings": [
            "Low coaching uncertainty — context informational only"
          ],
          "summary": "BUF 2026 (Weeks 1-4): blend favors prior-year team (70%). Continuity 80, uncertainty penalty 18. Treat offense as mostly stable; defensive/staff title changes should not materially change offensive prop priors."
        }
      },
      "createdAt": "2026-05-21T00:51:14.998Z"
    },
    {
      "id": "2025-w1-fixture-w1-pm-cook-rushatt",
      "season": 2025,
      "week": 1,
      "gameId": "fixture-buf-at-mia-w1",
      "playerId": "fixture-cook",
      "playerName": "James Cook",
      "team": "BUF",
      "opponent": "MIA",
      "propType": "RUSHING_ATTEMPTS",
      "line": 14.5,
      "lineBucket": "10.5 – 14.5",
      "marketOverProbability": 0.5348837209302325,
      "marketUnderProbability": 0.5121951219512195,
      "modelOverProbability": 0.7976716705783686,
      "modelUnderProbability": 0.20232832942163131,
      "edge": 0.2868374343920198,
      "edgeBucket": "≥ 10%",
      "recommendation": "PASS",
      "qualified": false,
      "confidence": 0.39793267023201795,
      "confidenceBucket": "Low",
      "primaryDisqualifier": "Role stability score 0.50 below 0.55 gate",
      "disqualifiers": [
        "Role stability score 0.50 below 0.55 gate"
      ],
      "riskScore": 0.6896633511600896,
      "dataQualityScore": 0.55,
      "roleStabilityScore": 0.5,
      "weatherRiskScore": 0.7666666666666666,
      "injuryRiskScore": 0.85,
      "coachingUncertaintyScore": 18,
      "correlationRiskScore": 0.8,
      "overOdds": -115,
      "underOdds": -105,
      "selectedOdds": -115,
      "selectedSide": "OVER",
      "actualStat": null,
      "result": "PASS",
      "profitLossUnits": 0,
      "counterfactualResult": "NO_RESULT",
      "counterfactualProfitLossUnits": 0,
      "postmortemTags": [],
      "scorecardSnapshot": {
        "scenarioName": "bt-2025-w1-fixture-w1-pm-cook-rushatt",
        "propId": "fixture-w1-pm-cook-rushatt",
        "playerName": "James Cook",
        "propType": "RUSHING_ATTEMPTS",
        "marketLine": 14.5,
        "overOdds": -115,
        "underOdds": -105,
        "marketOverProbability": 0.5348837209302325,
        "marketUnderProbability": 0.5121951219512195,
        "noVigOverProbability": 0.5108342361863488,
        "noVigUnderProbability": 0.4891657638136512,
        "projectedMean": 17,
        "projectedStdDev": 3,
        "modelOverProbability": 0.7976716705783686,
        "modelUnderProbability": 0.20232832942163131,
        "edgeOver": 0.2868374343920198,
        "edgeUnder": -0.28683743439201986,
        "selectedSide": "OVER",
        "edgeThreshold": 0.04,
        "recommendation": "PASS",
        "qualified": false,
        "confidence": 0.39793267023201795,
        "volatilityLevel": "low",
        "dataQualityScore": 0.55,
        "riskScore": 0.6896633511600896,
        "roleStabilityScore": 0.5,
        "gameScriptScore": 0.8214285714285714,
        "paceScore": 0.7,
        "marketContextScore": 0.5292115711854786,
        "weatherEnvironmentScore": 0.7666666666666666,
        "injuryContextScore": 0.85,
        "correlationExposureScore": 0.8,
        "passReasons": [
          "Model edge of +28.7% on OVER clears 4.0% threshold",
          "Model projects 79.8% hit rate vs no-vig 51.1%"
        ],
        "failReasons": [
          "Role stability 0.50 below 0.55 gate"
        ],
        "reasons": [
          "Role stability 0.50 below 0.55 gate"
        ],
        "risks": [
          "Market context 0.53 (above 0.45 gate but below 0.65 comfort zone)",
          "Data quality 0.55 (above 0.55 gate but below 0.65 comfort zone)",
          "Role stability 0.50 below 0.55 gate",
          "Low coaching uncertainty — context informational only"
        ],
        "disqualifiers": [
          "Role stability score 0.50 below 0.55 gate"
        ],
        "finalExplanation": "PASS on James Cook RUSHING_ATTEMPTS 14.5: OVER edge of +28.7% would qualify, but role stability score 0.50 is below the 0.55 gate.",
        "coachingTransition": {
          "team": "BUF",
          "season": 2026,
          "scores": {
            "coachingContinuityScore": 80,
            "offensivePlayCallerChangeScore": 15,
            "defensivePlayCallerChangeScore": 70,
            "teamTendencyTrustScore": 72,
            "offensiveIdentityShiftScore": 20,
            "defensiveIdentityShiftScore": 55,
            "playCallerConfidenceScore": 90,
            "coachingUncertaintyPenalty": 18
          },
          "blendWeights": {
            "priorTeam": 70,
            "coachProfile": 20,
            "leagueAverage": 10,
            "currentSeasonObserved": 0
          },
          "offensiveNotes": [],
          "defensiveNotes": [],
          "propImpacts": {
            "PASSING_ATTEMPTS": "neutral",
            "PASSING_COMPLETIONS": "neutral",
            "PASSING_YARDS": "neutral",
            "RECEPTIONS": "neutral",
            "RECEIVING_YARDS": "neutral",
            "RUSHING_ATTEMPTS": "neutral",
            "RUSHING_YARDS": "neutral"
          },
          "warnings": [
            "Low coaching uncertainty — context informational only"
          ],
          "summary": "BUF 2026 (Weeks 1-4): blend favors prior-year team (70%). Continuity 80, uncertainty penalty 18. Treat offense as mostly stable; defensive/staff title changes should not materially change offensive prop priors."
        }
      },
      "createdAt": "2026-05-21T00:51:14.998Z"
    }
  ]
}
